veeam_em/__init__.py
veeam_em/const.py
veeam_em/exceptions.py
veeam_em/helper.py
veeam_em/manager.py
veeam_em-2022.11.0.dist-info/LICENSE
veeam_em-2022.11.0.dist-info/METADATA
veeam_em-2022.11.0.dist-info/WHEEL
veeam_em-2022.11.0.dist-info/top_level.txt
veeam_em-2022.11.0.dist-info/RECORD
