Metadata-Version: 2.1
Name: veeam-em
Version: 2022.11.0
Summary: Veeam Enterprise Manager REST API Client
Home-page: https://gitlab-ee.eis.utoronto.ca/eis/veeam/veeam-em
Download-URL: https://gitlab-ee.eis.utoronto.ca/eis/veeam/veeam-em/archive/2022.11.0.zip
Author: University of Toronto
Author-email: vss-apps@eis.utoronto.ca
Maintainer-email: vss-py@eis.utoronto.ca
License: MIT
Project-URL: Bug Reports, https://gitlab-ee.eis.utoronto.ca/eis/veeam/veeam-em/issues
Project-URL: Documentation, https://eis.utoronto.ca/~vss/veeam-em/
Project-URL: Source, https://gitlab-ee.eis.utoronto.ca/eis/veeam/veeam-em
Platform: any
Classifier: Development Status :: 5 - Production/Stable
Classifier: Intended Audience :: System Administrators
Classifier: Intended Audience :: End Users/Desktop
Classifier: Intended Audience :: Developers
Classifier: License :: OSI Approved :: MIT License
Classifier: Operating System :: OS Independent
Classifier: Programming Language :: Python :: 3.7
Classifier: Programming Language :: Python :: 3.8
Classifier: Programming Language :: Python :: 3.9
Classifier: Programming Language :: Python :: 3.10
Classifier: Topic :: Software Development :: Libraries :: Python Modules
Classifier: Topic :: System :: Systems Administration
License-File: LICENSE
Requires-Dist: requests (>=2.23.0)
Provides-Extra: dev
Requires-Dist: flake8 (==3.7.7) ; extra == 'dev'
Requires-Dist: nose (==1.3.7) ; extra == 'dev'
Requires-Dist: coverage (==4.5.3) ; extra == 'dev'
Requires-Dist: pytz (==2018.9) ; extra == 'dev'
Requires-Dist: wheel (==0.33.1) ; extra == 'dev'
Requires-Dist: sphinx-rtd-theme (==0.4.3) ; extra == 'dev'
Requires-Dist: Sphinx (==1.8.5) ; extra == 'dev'
Provides-Extra: test
Requires-Dist: flake8 (==3.7.7) ; extra == 'test'
Requires-Dist: nose (==1.3.7) ; extra == 'test'
Requires-Dist: coverage (==4.5.3) ; extra == 'test'
Requires-Dist: pytz (==2018.9) ; extra == 'test'
Requires-Dist: wheel (==0.33.1) ; extra == 'test'
